LICENSE.txt
README.md
setup.cfg
setup.py
clippings/__init__.py
clippings/parser.py
clippings/utils.py
clippings.egg-info/PKG-INFO
clippings.egg-info/SOURCES.txt
clippings.egg-info/dependency_links.txt
clippings.egg-info/entry_points.txt
clippings.egg-info/not-zip-safe
clippings.egg-info/requires.txt
clippings.egg-info/top_level.txt