Metadata-Version: 2.1
Name: clippings
Version: 0.9.0
Summary: Amazon Kindle clippings parser
Home-page: https://github.com/samueldg/clippings/
Download-URL: https://github.com/samueldg/clippings/tarball/0.9.0
Author: Samuel Dion-Girardeau
Author-email: samuel.diongirardeau@gmail.com
License: MIT
Project-URL: Changelog, https://github.com/samueldg/clippings/blob/master/CHANGELOG.md
Keywords: amazon,kindle,clipping,e-book
Classifier: Development Status :: 4 - Beta
Classifier: License :: OSI Approved :: MIT License
Classifier: Natural Language :: English
Classifier: Operating System :: OS Independent
Classifier: Programming Language :: Python
Classifier: Programming Language :: Python :: 3
Classifier: Programming Language :: Python :: 3.7
Classifier: Programming Language :: Python :: 3.8
Classifier: Programming Language :: Python :: 3.9
Classifier: Programming Language :: Python :: 3.10
Classifier: Programming Language :: Python :: 3.11
Classifier: Topic :: Software Development :: Libraries :: Python Modules
Classifier: Topic :: Utilities
Requires-Python: >=3.7
License-File: LICENSE.txt
